Metadata-Version: 2.4
Name: prfr-data-streamlit-fork
Version: 0.3.1
Summary: A faster way to build and share data apps
Home-page: https://github.com/pernod-ricard-france-data/prfr-data-streamlit-fork
Author: Snowflake Inc
Author-email: hello@streamlit.io
License: Apache License 2.0
Project-URL: Source Code, https://github.com/pernod-ricard-france-data/prfr-data-streamlit-fork
Project-URL: Bug Tracker, https://github.com/pernod-ricard-france-data/prfr-data-streamlit-fork/issues
Project-URL: Release notes, https://github.com/pernod-ricard-france-data/prfr-data-streamlit-fork/releases
Project-URL: Documentation, https://docs.streamlit.io/
Project-URL: Community, https://discuss.streamlit.io/
Project-URL: Twitter, https://twitter.com/streamlit
Classifier: Development Status :: 5 - Production/Stable
Classifier: Environment :: Console
Classifier: Environment :: Web Environment
Classifier: Intended Audience :: Developers
Classifier: Intended Audience :: Science/Research
Classifier: License :: OSI Approved :: Apache Software License
Classifier: Programming Language :: Python :: 3.9
Classifier: Programming Language :: Python :: 3.10
Classifier: Programming Language :: Python :: 3.11
Classifier: Programming Language :: Python :: 3.12
Classifier: Programming Language :: Python :: 3.13
Classifier: Topic :: Database :: Front-Ends
Classifier: Topic :: Office/Business :: Financial :: Spreadsheet
Classifier: Topic :: Scientific/Engineering :: Information Analysis
Classifier: Topic :: Scientific/Engineering :: Visualization
Classifier: Topic :: Software Development :: Libraries :: Application Frameworks
Classifier: Topic :: Software Development :: Widget Sets
Requires-Python: >=3.9, !=3.9.7
Requires-Dist: altair<6,>=4.0
Requires-Dist: blinker<2,>=1.0.0
Requires-Dist: cachetools<6,>=4.0
Requires-Dist: click<9,>=7.0
Requires-Dist: numpy<3,>=1.23
Requires-Dist: pandas<3,>=1.4.0
Requires-Dist: pillow<12,>=7.1.0
Requires-Dist: pyarrow>=7.0
Requires-Dist: requests<3,>=2.27
Requires-Dist: tenacity<10,>=8.1.0
Requires-Dist: toml<2,>=0.10.1
Requires-Dist: typing-extensions<5,>=4.4.0
Requires-Dist: watchdog<7,>=2.1.5; platform_system != "Darwin"
Requires-Dist: gitpython!=3.1.19,<4,>=3.0.7
Requires-Dist: pydeck<1,>=0.8.0b4
Requires-Dist: tornado<7,>=6.0.3
Provides-Extra: snowflake
Requires-Dist: snowflake-snowpark-python[modin]>=1.17.0; python_version < "3.12" and extra == "snowflake"
Requires-Dist: snowflake-connector-python>=3.3.0; python_version < "3.12" and extra == "snowflake"
Dynamic: author
Dynamic: author-email
Dynamic: classifier
Dynamic: description-content-type
Dynamic: home-page
Dynamic: license
Dynamic: project-url
Dynamic: provides-extra
Dynamic: requires-dist
Dynamic: requires-python
Dynamic: summary
